YasinDataPrepKit/__init__.py
YasinDataPrepKit/dtk.py
yasDataPrepKit-0.4.1.dist-info/METADATA
yasDataPrepKit-0.4.1.dist-info/WHEEL
yasDataPrepKit-0.4.1.dist-info/top_level.txt
yasDataPrepKit-0.4.1.dist-info/RECORD
