Metadata-Version: 2.1
Name: yasDataPrepKit
Version: 0.4.1
Summary: This package can read data from a couple of different file types, can summarize data, handle missing values and can encode your data using one hot encoding.
Author: Yaseen Mohammed
Author-email: yasien202020@gmail.com
Classifier: Programming Language :: Python :: 3.12
Classifier: License :: OSI Approved :: MIT License
Classifier: Operating System :: OS Independent
Requires-Python: >=3.6
